LICENSE.txt
MANIFEST.in
README.md
setup.py
django_tabler/__init__.py
django_tabler/views.py
django_tabler.egg-info/PKG-INFO
django_tabler.egg-info/SOURCES.txt
django_tabler.egg-info/dependency_links.txt
django_tabler.egg-info/not-zip-safe
django_tabler.egg-info/top_level.txt
django_tabler/static/css/dashboard.css
django_tabler/static/css/dashboard.rtl.css
django_tabler/static/css/tabler.css
django_tabler/static/css/tabler.rtl.css
django_tabler/static/fonts/feather/feather-webfont.eot
django_tabler/static/fonts/feather/feather-webfont.svg
django_tabler/static/fonts/feather/feather-webfont.ttf
django_tabler/static/fonts/feather/feather-webfont.woff
django_tabler/static/fonts/font_awesome/font-awesome.min.css
django_tabler/static/fonts/google/source_sans_pro/source-sans-pro-v11-latin-600.eot
django_tabler/static/fonts/google/source_sans_pro/source-sans-pro-v11-latin-600.svg
django_tabler/static/fonts/google/source_sans_pro/source-sans-pro-v11-latin-600.ttf
django_tabler/static/fonts/google/source_sans_pro/source-sans-pro-v11-latin-600.woff
django_tabler/static/fonts/google/source_sans_pro/source-sans-pro-v11-latin-600.woff2
django_tabler/static/fonts/google/source_sans_pro/source-sans-pro-v11-latin-600italic.eot
django_tabler/static/fonts/google/source_sans_pro/source-sans-pro-v11-latin-600italic.svg
django_tabler/static/fonts/google/source_sans_pro/source-sans-pro-v11-latin-600italic.ttf
django_tabler/static/fonts/google/source_sans_pro/source-sans-pro-v11-latin-600italic.woff
django_tabler/static/fonts/google/source_sans_pro/source-sans-pro-v11-latin-600italic.woff2
django_tabler/static/fonts/google/source_sans_pro/source-sans-pro-v11-latin-italic.eot
django_tabler/static/fonts/google/source_sans_pro/source-sans-pro-v11-latin-italic.svg
django_tabler/static/fonts/google/source_sans_pro/source-sans-pro-v11-latin-italic.ttf
django_tabler/static/fonts/google/source_sans_pro/source-sans-pro-v11-latin-italic.woff
django_tabler/static/fonts/google/source_sans_pro/source-sans-pro-v11-latin-italic.woff2
django_tabler/static/fonts/google/source_sans_pro/source-sans-pro-v11-latin-regular.eot
