Metadata-Version: 1.1
Name: django-tabler
Version: 0.0.32
Summary: Django static files & templates for the Tabler dashboard
Home-page: https://github.com/rbennett91/django-tabler
Author: Ryan Bennett
Author-email: ryan.bennett@outlook.com
License: UNKNOWN
Keywords: django,tabler,dashboard,template,ui
Platform: UNKNOWN
Classifier: Development Status :: 4 - Beta
Classifier: Environment :: Web Environment
Classifier: Framework :: Django
Classifier: Framework :: Django :: 1.11
Classifier: License :: OSI Approved :: MIT License
Classifier: Operating System :: OS Independent
Classifier: Programming Language :: JavaScript
Classifier: Programming Language :: Python :: 3
Classifier: Programming Language :: Python :: 3.6
Classifier: Topic :: Internet :: WWW/HTTP
Classifier: Topic :: Internet :: WWW/HTTP :: Dynamic Content
Classifier: Topic :: Software Development :: Libraries :: Python Modules
